pyrandomsearch/__init__.py
pyrandomsearch/pyrandomsearch.py
pyrandomsearch/test/__init__.py
pyrandomsearch/test/cli.py
pyrandomsearch/test/test_error_checking.py
pyrandomsearch/test/test_options.py
pyrandomsearch/test/test_simple_nominal_behavior.py
pyrandomsearch-0.1.0.dist-info/METADATA
pyrandomsearch-0.1.0.dist-info/RECORD
pyrandomsearch-0.1.0.dist-info/WHEEL
pyrandomsearch-0.1.0.dist-info/entry_points.txt
pyrandomsearch-0.1.0.dist-info/top_level.txt
